README.rst
setup.py
django_grains.egg-info/PKG-INFO
django_grains.egg-info/SOURCES.txt
django_grains.egg-info/dependency_links.txt
django_grains.egg-info/top_level.txt
grains/__init__.py
grains/admin.py
grains/models.py
grains/migrations/0001_initial.py
grains/migrations/0002_auto__add_grain.py
grains/migrations/__init__.py
grains/templatetags/__init__.py
grains/templatetags/grains_tags.py