Metadata-Version: 1.1
Name: django-grains
Version: 0.2.1
Summary: Define content fragments in Django templates and store their contents in the database. This is yet another take on the idea previously implemented in django-flatblocks, django-chunks etc.
Home-page: http://github.com/2general/django-grains
Author: Antti Kaihola (2General Ltd.)
Author-email: antti@2general.com
License: UNKNOWN
Platform: UNKNOWN
Classifier: Development Status :: 4 - Beta
Classifier: Framework :: Django
Classifier: Intended Audience :: Developers
Classifier: Operating System :: OS Independent
Classifier: Programming Language :: Python
Classifier: Topic :: Internet :: WWW/HTTP
Classifier: License :: OSI Approved :: BSD License
